Metadata-Version: 2.1
Name: ovos-voice-embeddings-plugin
Version: 0.0.0a2
Summary: A voice recognition plugin for OVOS
Home-page: https://github.com/TigreGotico/ovos-voice-embeddings-plugin
Author: jarbasai
Author-email: jarbasai@mailfence.com
License: MIT
Keywords: OVOS openvoiceos plugin voice recognition
Platform: UNKNOWN
Requires-Dist: ovos-plugin-manager
Requires-Dist: numpy
Requires-Dist: ovos-chromadb-embeddings-plugin
Requires-Dist: resemblyzer
